[{"name":"ABS","hp":"59","posX":"1","posY":"2","posZ":"3","rotX":"37","rotY":"4","rotZ":"8"},{"name":"fanot","hp":100,"posX":-4.7539,"posY":0,"posZ":2.547588,"rotX":-0,"rotY":118.1866,"rotZ":0},{"name":"yuiop","hp":100,"posX":7.555934,"posY":0,"posZ":-7.287923,"rotX":-0,"rotY":-85.885452,"rotZ":-0},{"name":"kolpi","hp":100,"posX":5.249694,"posY":0,"posZ":-11.896193,"rotX":-0,"rotY":-26.664259,"rotZ":-0},{"name":"kopopl","hp":100,"posX":-4.379584,"posY":0,"posZ":-0.753514,"rotX":-0,"rotY":-157.309906,"rotZ":0}]